storage_interfaces/__init__.py
storage_interfaces/__version__.py
storage_interfaces/_compat.py
storage_interfaces/abstracts.py
storage_interfaces/scsi/__init__.py
storage_interfaces/scsi/abstracts.py
unnamed7389-1.0.3.dist-info/DESCRIPTION.rst
unnamed7389-1.0.3.dist-info/METADATA
unnamed7389-1.0.3.dist-info/RECORD
unnamed7389-1.0.3.dist-info/WHEEL
unnamed7389-1.0.3.dist-info/metadata.json
unnamed7389-1.0.3.dist-info/namespace_packages.txt
unnamed7389-1.0.3.dist-info/top_level.txt
